pysigep/__init__.py
pysigep/__version__.py
pysigep/client.py
pysigep/utils.py
pysigep-0.1.0.dist-info/METADATA
pysigep-0.1.0.dist-info/RECORD
pysigep-0.1.0.dist-info/WHEEL
pysigep-0.1.0.dist-info/top_level.txt
