Metadata-Version: 1.2
Name: pysigep
Version: 0.1.0
Summary: API python para uso dos serviços fornecidos pelo SIGEPWeb dos Correios 
Home-page: https://github.com/mstuttgart/pysigep
Author: Michell Stuttgart
Author-email: michellstut@gmail.com
Maintainer: Michell Stuttgart
Maintainer-email: michellstut@gmail.com
License: MIT License
Download-URL: https://github.com/mstuttgart/pysigep
Keywords: correios sigep sigepweb development api
Platform: any
Classifier: Development Status :: 4 - Beta
Classifier: Intended Audience :: Developers
Classifier: Natural Language :: Portuguese
Classifier: License :: OSI Approved :: MIT License
Classifier: Programming Language :: Python :: 3.5
Classifier: Programming Language :: Python :: 3.6
